alchemical_clone/__init__.py
alchemical_clone/alchemical_column.py
alchemical_clone/alchemical_constraint.py
alchemical_clone/alchemical_index.py
alchemical_clone/alchemical_lab.py
alchemical_clone/alchemical_table.py
alchemical_clone/generated_code.py
alchemical_clone/plugins/__init__.py
alchemical_clone/plugins/many_to_many.py
alchemical_clone/plugins/one_to_many.py
alchemical_clone/utils/__init__.py
alchemical_clone/utils/utils.py
alchemical_clone-0.0.2.dist-info/LICENSE
alchemical_clone-0.0.2.dist-info/METADATA
alchemical_clone-0.0.2.dist-info/WHEEL
alchemical_clone-0.0.2.dist-info/top_level.txt
alchemical_clone-0.0.2.dist-info/RECORD
