Metadata-Version: 2.1
Name: alchemical_clone
Version: 0.0.2
Summary: A Python package for generating SQLAlchemy ORM code from an existing database
Author-email: Francisco Rodrigues <francisco.rodrigues@gmail.com>
Project-URL: Homepage, https://github.com/ArmindoFlores/alchemical-clone
Project-URL: Issues, https://github.com/ArmindoFlores/alchemical-clone/issues
Classifier: Programming Language :: Python :: 3
Classifier: Operating System :: OS Independent
Classifier: Intended Audience :: Developers
Classifier: License :: OSI Approved :: MIT License
Classifier: Topic :: Database
Requires-Python: >=3.10
License-File: LICENSE
Requires-Dist: SQLAlchemy >=2.0.25
